UtilityTools/__init__.py
UtilityTools/main.py
utility_tools-1.4.0.dist-info/LICENSE
utility_tools-1.4.0.dist-info/METADATA
utility_tools-1.4.0.dist-info/WHEEL
utility_tools-1.4.0.dist-info/entry_points.txt
utility_tools-1.4.0.dist-info/top_level.txt
utility_tools-1.4.0.dist-info/RECORD
