Metadata-Version: 2.2
Name: utility-tools
Version: 1.4.0
Summary: A comprehensive Python utility module that provides various tools for common tasks
Home-page: https://github.com/Good-Wizard/UtilityTools
Author: Good-Wizard
Author-email: arashrahbarxz@gmail.com
Project-URL: Bug Reports, https://github.com/Good-Wizard/UtilityTools/issues
Project-URL: Source, https://github.com/Good-Wizard/UtilityTools
Keywords: utility,tools,qrcode,bmi,temperature,password,file handling,compression,geometry,datetime,http
Classifier: Development Status :: 5 - Production/Stable
Classifier: Intended Audience :: Developers
Classifier: Topic :: Software Development :: Libraries :: Python Modules
Classifier: License :: OSI Approved :: MIT License
Classifier: Programming Language :: Python :: 3
Classifier: Programming Language :: Python :: 3.7
Classifier: Programming Language :: Python :: 3.8
Classifier: Programming Language :: Python :: 3.9
Classifier: Programming Language :: Python :: 3.10
Classifier: Programming Language :: Python :: 3.11
Classifier: Operating System :: OS Independent
Requires-Python: >=3.7
License-File: LICENSE
Requires-Dist: qrcode>=7.3
Requires-Dist: Pillow>=9.0.0
Requires-Dist: pytz>=2021.1
Requires-Dist: requests>=2.26.0
Dynamic: author
Dynamic: author-email
Dynamic: classifier
Dynamic: description
Dynamic: description-content-type
Dynamic: home-page
Dynamic: keywords
Dynamic: project-url
Dynamic: requires-dist
Dynamic: requires-python
Dynamic: summary
